README.md
setup.py
amz_ppc_optimizer/__init__.py
amz_ppc_optimizer/settings.py
amz_ppc_optimizer.egg-info/PKG-INFO
amz_ppc_optimizer.egg-info/SOURCES.txt
amz_ppc_optimizer.egg-info/dependency_links.txt
amz_ppc_optimizer.egg-info/requires.txt
amz_ppc_optimizer.egg-info/top_level.txt
amz_ppc_optimizer/amz_sheet_handler/__init__.py
amz_ppc_optimizer/amz_sheet_handler/core.py
amz_ppc_optimizer/amz_sheet_handler/utils.py
amz_ppc_optimizer/apex_optimizer/__init__.py
amz_ppc_optimizer/apex_optimizer/core.py
amz_ppc_optimizer/apex_optimizer/utils.py
amz_ppc_optimizer/placement_optimizer/__init__.py
amz_ppc_optimizer/placement_optimizer/core.py
amz_ppc_optimizer/placement_optimizer/utils.py
amz_ppc_optimizer/search_term_optimizer/__init__.py
amz_ppc_optimizer/search_term_optimizer/core.py
amz_ppc_optimizer/search_term_optimizer/utils.py
tests/__init__.py
tests/test_core.py
tests/test_utils.py
utils/__init__.py
utils/utils.py