Metadata-Version: 2.1
Name: amz-ppc-optimizer
Version: 0.1.7
Summary: Python package for optimizing Amazon advertising campaigns
Home-page: https://github.com/ehsanmqn/amz-ppc-optimizer
Author: Ehsan Maiqani
Author-email: ehsan.maiqani@gmail.com
Classifier: Programming Language :: Python :: 3
Classifier: License :: OSI Approved :: MIT License
Classifier: Operating System :: OS Independent
